[
    {
        "key": "dbln",
        "value": "%7B%2261579975353913%22%3A%223JqWQ7JC%22%7D",
        "domain": "facebook.com",
        "path": "/login/device-based/",
        "hostOnly": false,
        "creation": "2025-08-30T14:36:43.431Z",
        "lastAccessed": "2025-08-30T14:36:43.432Z"
    },
    {
        "key": "datr",
        "value": "xQuzaPjAqhExKvHxqNgDKeZ1",
        "domain": "facebook.com",
        "path": "/",
        "hostOnly": false,
        "creation": "2025-08-30T14:36:43.432Z",
        "lastAccessed": "2025-08-30T14:36:43.432Z"
    },
    {
        "key": "locale",
        "value": "en_US",
        "domain": "facebook.com",
        "path": "/",
        "hostOnly": false,
        "creation": "2025-08-30T14:36:43.432Z",
        "lastAccessed": "2025-08-30T14:36:43.432Z"
    },
    {
        "key": "vpd",
        "value": "v1%3B688x360x2",
        "domain": "facebook.com",
        "path": "/",
        "hostOnly": false,
        "creation": "2025-08-30T14:36:43.432Z",
        "lastAccessed": "2025-08-30T14:36:43.432Z"
    },
    {
        "key": "ps_l",
        "value": "1",
        "domain": "facebook.com",
        "path": "/",
        "hostOnly": false,
        "creation": "2025-08-30T14:36:43.432Z",
        "lastAccessed": "2025-08-30T14:36:43.432Z"
    },
    {
        "key": "ps_n",
        "value": "1",
        "domain": "facebook.com",
        "path": "/",
        "hostOnly": false,
        "creation": "2025-08-30T14:36:43.432Z",
        "lastAccessed": "2025-08-30T14:36:43.432Z"
    },
    {
        "key": "sb",
        "value": "2QuzaGsYc04mmC5vt9al5ziQ",
        "domain": "facebook.com",
        "path": "/",
        "hostOnly": false,
        "creation": "2025-08-30T14:36:43.432Z",
        "lastAccessed": "2025-08-30T14:36:43.432Z"
    },
    {
        "key": "m_pixel_ratio",
        "value": "2",
        "domain": "facebook.com",
        "path": "/",
        "hostOnly": false,
        "creation": "2025-08-30T14:36:43.432Z",
        "lastAccessed": "2025-08-30T14:36:43.432Z"
    },
    {
        "key": "wd",
        "value": "360x800",
        "domain": "facebook.com",
        "path": "/",
        "hostOnly": false,
        "creation": "2025-08-30T14:36:43.432Z",
        "lastAccessed": "2025-08-30T14:36:43.432Z"
    },
    {
        "key": "c_user",
        "value": "61579975353913",
        "domain": "facebook.com",
        "path": "/",
        "hostOnly": false,
        "creation": "2025-08-30T14:36:43.432Z",
        "lastAccessed": "2025-08-30T14:36:43.432Z"
    },
    {
        "key": "fr",
        "value": "0ymtOaLFUvsUz4Hsz.AWeabk-FXucW_9UQlS3JPDiqkuzjNWSG2Pcogz5bjIDRNCjRUf8.BoswvF..AAA.0.0.BoswwH.AWdkaPn_vMXo2HjYLjiqgE79hos",
        "domain": "facebook.com",
        "path": "/",
        "hostOnly": false,
        "creation": "2025-08-30T14:36:43.432Z",
        "lastAccessed": "2025-08-30T14:36:43.432Z"
    },
    {
        "key": "xs",
        "value": "8%3Ai7vX7NkQOWi2JA%3A2%3A1756564488%3A-1%3A-1",
        "domain": "facebook.com",
        "path": "/",
        "hostOnly": false,
        "creation": "2025-08-30T14:36:43.432Z",
        "lastAccessed": "2025-08-30T14:36:43.432Z"
    },
    {
        "key": "pas",
        "value": "61579975353913%3ASPL6uJjkQ0",
        "domain": "facebook.com",
        "path": "/",
        "hostOnly": false,
        "creation": "2025-08-30T14:36:43.432Z",
        "lastAccessed": "2025-08-30T14:36:43.432Z"
    },
    {
        "key": "fbl_st",
        "value": "101635302%3BT%3A29276074",
        "domain": "facebook.com",
        "path": "/",
        "hostOnly": false,
        "creation": "2025-08-30T14:36:43.432Z",
        "lastAccessed": "2025-08-30T14:36:43.432Z"
    },
    {
        "key": "wl_cbv",
        "value": "v2%3Bclient_version%3A2908%3Btimestamp%3A1756564493",
        "domain": "facebook.com",
        "path": "/",
        "hostOnly": false,
        "creation": "2025-08-30T14:36:43.432Z",
        "lastAccessed": "2025-08-30T14:36:43.432Z"
    }
]


        



